setup.py
legos/__init__.py
legos/dice.py
legos.dice.egg-info/PKG-INFO
legos.dice.egg-info/SOURCES.txt
legos.dice.egg-info/dependency_links.txt
legos.dice.egg-info/namespace_packages.txt
legos.dice.egg-info/requires.txt
legos.dice.egg-info/top_level.txt