Metadata-Version: 1.1
Name: legos.dice
Version: 0.1.0
Summary: Dice rolling plugin for Legobot
Home-page: https://github.com/bbriggs/legos.dice
Author: Brenton Briggs II
Author-email: UNKNOWN
License: GPLv3
Platform: UNKNOWN
Classifier: License :: OSI Approved :: GNU General Public License v3 (GPLv3)
Classifier: Programming Language :: Python :: 3
